[
    {
        "Date": "2025-03-24 23:32:58",
        "Performance Score": 0.0190019597898589
    },
    {
        "Date": "2025-03-25 00:43:42",
        "Performance Score": 0.019856763100402755
    },
    {
        "Date": "2025-03-26 00:42:51",
        "Performance Score": 0.019856763100402755
    },
    {
        "Date": "2025-03-27 00:43:08",
        "Performance Score": 0.019856763100402755
    },
    {
        "Date": "2025-03-28 00:42:55",
        "Performance Score": 0.019856763100402755
    },
    {
        "Date": "2025-03-29 00:42:51",
        "Performance Score": 0.019856763100402755
    },
    {
        "Date": "2025-03-30 00:47:17",
        "Performance Score": 0.01985675506456903
    },
    {
        "Date": "2025-03-31 00:46:17",
        "Performance Score": 0.06497581068553299
    }
]